{
  "title": "1064. Great Is Thy Faithfulness",
  "parts": {
    "S": {
      "title": "Soprano",
      "url": "https://www.dahl-fam.com/sing-sync/1064.%20Great%20Is%20Thy%20Faithfulness/Soprano.wav"
    },
    "A": {
      "title": "Alto",
      "url": "https://www.dahl-fam.com/sing-sync/1064.%20Great%20Is%20Thy%20Faithfulness/Alto.wav"
    },
    "T": {
      "title": "Tenor",
      "url": "https://www.dahl-fam.com/sing-sync/1064.%20Great%20Is%20Thy%20Faithfulness/Tenor.wav"
    },
    "B": {
      "title": "Bass",
      "url": "https://www.dahl-fam.com/sing-sync/1064.%20Great%20Is%20Thy%20Faithfulness/Bass.wav"
    }
  }
}